orion/__init__.py
orion/client.py
orion/historic.py
orion/mmsi.py
orion/types/__init__.py
orion/types/ais.py
orion/urls.py
orion/utils/__init__.py
orion/utils/get_data.py
orion/vessel_codes.py
orion_nais-0.2.0.dist-info/LICENSE
orion_nais-0.2.0.dist-info/WHEEL
orion_nais-0.2.0.dist-info/METADATA
orion_nais-0.2.0.dist-info/RECORD
