Metadata-Version: 2.1
Name: orion-nais
Version: 0.2.0
Summary: A client for the NAIS API from FThe Norwegian Coastal Administration
Home-page: https://github.com/BergensTidende/orion-nais
License: MIT
Author: Lasse Lambrechts
Author-email: lasse.lambrechts@bt.no
Requires-Python: >=3.10,<4.0
Classifier: License :: OSI Approved :: MIT License
Classifier: Programming Language :: Python :: 3
Classifier: Programming Language :: Python :: 3.10
Classifier: Programming Language :: Python :: 3.11
Requires-Dist: geopandas (>=0.12.2,<0.13.0)
Requires-Dist: pandas (>=1.5.2,<2.0.0)
Requires-Dist: python-dotenv (>=0.21.0,<0.22.0)
Requires-Dist: pytz (>=2022.7.1,<2023.0.0)
Requires-Dist: requests (>=2.28.0,<3.0.0)
Requires-Dist: shapely (>=2.0.0,<3.0.0)
Project-URL: Repository, https://github.com/BergensTidende/orion-nais
